colour_checker_detection/__init__.py
colour_checker_detection/py.typed
colour_checker_detection/detection/__init__.py
colour_checker_detection/detection/common.py
colour_checker_detection/detection/inference.py
colour_checker_detection/detection/segmentation.py
colour_checker_detection/detection/tests/__init__.py
colour_checker_detection/detection/tests/test_common.py
colour_checker_detection/detection/tests/test_inference.py
colour_checker_detection/detection/tests/test_segmentation.py
colour_checker_detection/examples/examples_detection_inference.ipynb
colour_checker_detection/examples/examples_detection_segmentation.ipynb
colour_checker_detection/resources/colour-checker-detection-examples-datasets/.git
colour_checker_detection/resources/colour-checker-detection-tests-datasets/.git
colour_checker_detection/resources/colour-checker-detection-tests-datasets/.gitignore
colour_checker_detection/scripts/LICENSE
colour_checker_detection/scripts/inference.py
colour_checker_detection-0.2.1.dist-info/METADATA
colour_checker_detection-0.2.1.dist-info/WHEEL
colour_checker_detection-0.2.1.dist-info/entry_points.txt
colour_checker_detection-0.2.1.dist-info/licenses/LICENSE
colour_checker_detection-0.2.1.dist-info/RECORD
