Metadata-Version: 2.3
Name: colour-checker-detection
Version: 0.2.1
Summary: Colour checker detection with Python
Project-URL: Homepage, https://www.colour-science.org
Project-URL: Documentation, https://colour-checker-detection.readthedocs.org
Project-URL: Repository, https://github.com/colour-science/colour-checker-detection
Project-URL: Issues, https://github.com/colour-science/colour-checker-detection/issues
Project-URL: Changelog, https://github.com/colour-science/colour-checker-detection/releases
Author-email: Colour Developers <colour-developers@colour-science.org>
Maintainer-email: Colour Developers <colour-developers@colour-science.org>
License: BSD-3-Clause
License-File: LICENSE
Keywords: color,color-checker,color-science,color-space,color-spaces,colorspace,colorspaces,colour,colour-checker,colour-science,colour-space,colour-spaces,colourspace,colourspaces,python,segmentation
Classifier: Development Status :: 3 - Alpha
Classifier: Environment :: Console
Classifier: Intended Audience :: Developers
Classifier: Intended Audience :: Science/Research
Classifier: License :: OSI Approved
Classifier: Natural Language :: English
Classifier: Operating System :: OS Independent
Classifier: Programming Language :: Python :: 3
Classifier: Topic :: Scientific/Engineering
Classifier: Topic :: Software Development
Requires-Python: <3.14,>=3.10
Requires-Dist: colour-science>=0.4.4
Requires-Dist: imageio<3,>=2
Requires-Dist: numpy<3,>=1.24
Requires-Dist: opencv-python<5,>=4
Requires-Dist: scipy<2,>=1.10
Requires-Dist: typing-extensions<5,>=4
Provides-Extra: docs
Requires-Dist: biblib-simple; extra == 'docs'
Requires-Dist: pydata-sphinx-theme; extra == 'docs'
Requires-Dist: restructuredtext-lint; extra == 'docs'
Requires-Dist: sphinx; extra == 'docs'
Requires-Dist: sphinxcontrib-bibtex; extra == 'docs'
Provides-Extra: optional
Requires-Dist: matplotlib>=3.7; extra == 'optional'
Provides-Extra: ultralytics
Requires-Dist: click<9,>=8; (python_version < '3.13') and extra == 'ultralytics'
Requires-Dist: ultralytics<9,>=8; (python_version < '3.13') and extra == 'ultralytics'
